README.md
setup.cfg
setup.py
pyreess/__init__.py
pyreess/generator.py
pyreess/main.py
pyreess.egg-info/PKG-INFO
pyreess.egg-info/SOURCES.txt
pyreess.egg-info/dependency_links.txt
pyreess.egg-info/entry_points.txt
pyreess.egg-info/requires.txt
pyreess.egg-info/top_level.txt