Metadata-Version: 2.1
Name: pyreess
Version: 1.0
Summary: CLI application for deterministic password generation and recall
Home-page: https://github.com/BananaLoaf/pyreess
Author: BananaLoaf
Author-email: bananaloaf@protonmail.com
License: MIT
Project-URL: How secure is my password?, https://howsecureismypassword.net
Keywords: deterministic,password,generator
Platform: UNKNOWN
Classifier: Development Status :: 5 - Production/Stable
Classifier: Environment :: Console
Classifier: License :: OSI Approved :: MIT License
Classifier: Operating System :: OS Independent
Classifier: Programming Language :: Python :: 3
